{
  "maif_version": "0.1.0",
  "created": 1752428318.012768,
  "creator_id": null,
  "agent_id": "default_agent",
  "header": {
    "version": "0.1.0",
    "created_timestamp": 1752428318.012768,
    "creator_id": null,
    "agent_id": "default_agent"
  },
  "blocks": [
    {
      "type": "XMOD",
      "block_type": "XMOD",
      "offset": 0,
      "size": 31108,
      "hash": "2acd655a073f1e655cc0d2048d4d22dad81d52d2a882d92b54983d7dc1b46348",
      "version": 1,
      "previous_hash": null,
      "block_id": "5a188d71-b075-415a-a2a1-6891b40ae98b",
      "metadata": {
        "title": "Quick Multimodal Demo",
        "algorithm": "Enhanced_ACAM_v2",
        "modalities": [
          "text",
          "description",
          "category"
        ],
        "unified_representation_dim": 384,
        "attention_weights_available": true,
        "enhanced_version": true
      }
    }
  ],
  "version_history": {
    "5a188d71-b075-415a-a2a1-6891b40ae98b": [
      {
        "version": 1,
        "timestamp": 1752428318.0613172,
        "agent_id": "default_agent",
        "operation": "create",
        "block_id": "5a188d71-b075-415a-a2a1-6891b40ae98b",
        "previous_hash": null,
        "current_hash": "2acd655a073f1e655cc0d2048d4d22dad81d52d2a882d92b54983d7dc1b46348",
        "block_hash": "2acd655a073f1e655cc0d2048d4d22dad81d52d2a882d92b54983d7dc1b46348",
        "change_description": "Created cross_modal block"
      }
    ]
  },
  "block_registry": {
    "5a188d71-b075-415a-a2a1-6891b40ae98b": [
      {
        "type": "XMOD",
        "block_type": "XMOD",
        "offset": 0,
        "size": 31108,
        "hash": "2acd655a073f1e655cc0d2048d4d22dad81d52d2a882d92b54983d7dc1b46348",
        "version": 1,
        "previous_hash": null,
        "block_id": "5a188d71-b075-415a-a2a1-6891b40ae98b",
        "metadata": {
          "title": "Quick Multimodal Demo",
          "algorithm": "Enhanced_ACAM_v2",
          "modalities": [
            "text",
            "description",
            "category"
          ],
          "unified_representation_dim": 384,
          "attention_weights_available": true,
          "enhanced_version": true
        }
      }
    ]
  },
  "root_hash": "sha256:3886212dc4ac3fc7847932f1c2c0698dfa83f2dabb1718bff36072496295a6b1"
}